MANIFEST.in
README.md
setup.cfg
setup.py
fast_ta/__init__.py
fast_ta.egg-info/PKG-INFO
fast_ta.egg-info/SOURCES.txt
fast_ta.egg-info/dependency_links.txt
fast_ta.egg-info/requires.txt
fast_ta.egg-info/top_level.txt
fast_ta/src/BUILD
fast_ta/src/CMakeLists.txt
fast_ta/src/array_pair.h
fast_ta/src/debug_tools.c
fast_ta/src/debug_tools.h
fast_ta/src/error_methods.c
fast_ta/src/error_methods.h
fast_ta/src/funcs.c
fast_ta/src/funcs.h
fast_ta/src/momentum.c
fast_ta/src/momentum_backend.c
fast_ta/src/momentum_backend.h
fast_ta/src/momentum_backend_args.h
fast_ta/src/parallel_momentum_backend.c
fast_ta/src/parallel_momentum_backend.h
fast_ta/src/.idea/.gitignore
fast_ta/src/.idea/.name
fast_ta/src/.idea/fast-ta.iml
fast_ta/src/.idea/misc.xml
fast_ta/src/.idea/modules.xml
fast_ta/src/.idea/vcs.xml
fast_ta/src/.idea/workspace.xml
fast_ta/src/.idea/codeStyles/codeStyleConfig.xml
fast_ta/src/.ipynb_checkpoints/CMakeLists-checkpoint.txt
fast_ta/src/.ipynb_checkpoints/__init__-checkpoint.py
fast_ta/src/.ipynb_checkpoints/momentum-checkpoint.c
fast_ta/src/.ipynb_checkpoints/momentum_backend-checkpoint.c
fast_ta/src/.ipynb_checkpoints/momentum_backend-checkpoint.h
fast_ta/src/.ipynb_checkpoints/parallel_momentum_backend-checkpoint.c
fast_ta/src/.ipynb_checkpoints/setup-checkpoint.py
fast_ta/src/.ipynb_checkpoints/tests-checkpoint.py
fast_ta/src/cmake-build-debug/CMakeCache.txt
fast_ta/src/cmake-build-debug/Makefile
fast_ta/src/cmake-build-debug/cmake_install.cmake
fast_ta/src/cmake-build-debug/fast_ta.cbp
fast_ta/src/cmake-build-debug/CMakeFiles/CMakeDirectoryInformation.cmake
fast_ta/src/cmake-build-debug/CMakeFiles/CMakeOutput.log
fast_ta/src/cmake-build-debug/CMakeFiles/Makefile.cmake
fast_ta/src/cmake-build-debug/CMakeFiles/Makefile2
fast_ta/src/cmake-build-debug/CMakeFiles/TargetDirectories.txt
fast_ta/src/cmake-build-debug/CMakeFiles/clion-environment.txt
fast_ta/src/cmake-build-debug/CMakeFiles/clion-log.txt
fast_ta/src/cmake-build-debug/CMakeFiles/cmake.check_cache
fast_ta/src/cmake-build-debug/CMakeFiles/progress.marks
fast_ta/src/cmake-build-debug/CMakeFiles/3.15.3/CMakeCCompiler.cmake
